{
  "VideoPlaybackStateEvent": {
    "ClassSize": "0x18",
    "Attributes": [
      {
        "Name": "MediaTextureName",
        "Type": "Struct FString",
        "Size": "0x10",
        "Offset": "0x0"
      },
      {
        "Name": "State",
        "Type": "byte",
        "Size": "0x1",
        "Offset": "0x10"
      }
    ]
  },
  "VideoSubtitleEvent": {
    "ClassSize": "0x28",
    "Attributes": [
      {
        "Name": "MediaTextureName",
        "Type": "Struct FString",
        "Size": "0x10",
        "Offset": "0x0"
      },
      {
        "Name": "SubtitleString",
        "Type": "Struct FString",
        "Size": "0x10",
        "Offset": "0x10"
      },
      {
        "Name": "SubtitleDuration",
        "Type": "double",
        "Size": "0x8",
        "Offset": "0x20"
      }
    ]
  },
  "VideoPlaybackStopEvent": {
    "ClassSize": "0x10",
    "Attributes": [
      {
        "Name": "MediaTextureName",
        "Type": "Struct FString",
        "Size": "0x10",
        "Offset": "0x0"
      }
    ]
  },
  "VideoPlaybackPauseEvent": {
    "ClassSize": "0x10",
    "Attributes": [
      {
        "Name": "MediaTextureName",
        "Type": "Struct FString",
        "Size": "0x10",
        "Offset": "0x0"
      }
    ]
  },
  "VideoPlaybackStartEvent": {
    "ClassSize": "0x10",
    "Attributes": [
      {
        "Name": "MediaTextureName",
        "Type": "Struct FString",
        "Size": "0x10",
        "Offset": "0x0"
      }
    ]
  },
  "VideoPlaybackLoadEvent": {
    "ClassSize": "0x20",
    "Attributes": [
      {
        "Name": "MediaTextureName",
        "Type": "Struct FString",
        "Size": "0x10",
        "Offset": "0x0"
      },
      {
        "Name": "VideoUri",
        "Type": "Struct FString",
        "Size": "0x10",
        "Offset": "0x10"
      }
    ]
  },
  "MediaPlayedTelemetryEvent": {
    "ClassSize": "0x40",
    "Attributes": [
      {
        "Name": "MediaName",
        "Type": "Struct FString",
        "Size": "0x10",
        "Offset": "0x0"
      },
      {
        "Name": "LowestResolution",
        "Type": "Struct IntPoint",
        "Size": "0x8",
        "Offset": "0x10"
      },
      {
        "Name": "MedianResolution",
        "Type": "Struct IntPoint",
        "Size": "0x8",
        "Offset": "0x18"
      },
      {
        "Name": "HighestResolution",
        "Type": "Struct IntPoint",
        "Size": "0x8",
        "Offset": "0x20"
      }
    ]
  },
  "DougTheDruid": {
    "Notes": "Generated by DougTheDruid#2784 on Discord",
    "Reference": "https://github.com/DougTheDruid"
  }
}