{
  "BP_PuzzleVaultContextualTutorial_PromptCoordinator_C": {
    "Super": "BP_PromptCoordinator_Base_C",
    "FullSize": "0x218",
    "InheritedSize": "0x138",
    "ClassSize": "0xe0",
    "Attributes": [
      {
        "Name": "UberGraphFrame",
        "Type": "struct PointerToUberGraphFrame",
        "Size": "0x8",
        "Offset": "0x138"
      },
      {
        "Name": "pad0x6f_QRNP4[0x6f]",
        "Type": "char",
        "Size": "0x6f",
        "Offset": "0x140"
      },
      {
        "Name": "PopupRequestReceived",
        "Type": "bool",
        "Size": "0x1",
        "Offset": "0x140"
      },
      {
        "Name": "pad0x7_JZFZC[0x7]",
        "Type": "char",
        "Size": "0x7",
        "Offset": "0x141"
      },
      {
        "Name": "TreasureVaultContextualTutorialRequestHandle",
        "Type": "struct ObjectMessagingHandle",
        "Size": "0x58",
        "Offset": "0x148"
      },
      {
        "Name": "LocalPromptAccessKey",
        "Type": "class UClass*",
        "Size": "0x8",
        "Offset": "0x1a0"
      },
      {
        "Name": "PuzzleVaultTutorialPopup",
        "Type": "struct PrioritisedPromptWithHandle",
        "Size": "0x70",
        "Offset": "0x1a8"
      }
    ]
  },
  "DougTheDruid": {
    "Notes": "Generated by dougthedruid on Discord",
    "Reference": "https://github.com/DougTheDruid"
  }
}