{
  "BP_SmallShip_DamageZone_LowerDeck_00_C": {
    "Super": "BP_BaseInternalDamageZone_C",
    "FullSize": "0x868",
    "InheritedSize": "0x868",
    "ClassSize": "0x0",
    "Attributes": []
  },
  "BP_SmallShip_DamageZone_LowerDeck_01_C": {
    "Super": "BP_BaseInternalDamageZone_C",
    "FullSize": "0x868",
    "InheritedSize": "0x868",
    "ClassSize": "0x0",
    "Attributes": []
  },
  "BP_SmallShip_DamageZone_MezzanineDeck_00_C": {
    "Super": "BP_BaseInternalDamageZone_C",
    "FullSize": "0x868",
    "InheritedSize": "0x868",
    "ClassSize": "0x0",
    "Attributes": []
  },
  "BP_SmallShip_DamageZone_MezzanineDeck_01_C": {
    "Super": "BP_BaseInternalDamageZone_C",
    "FullSize": "0x868",
    "InheritedSize": "0x868",
    "ClassSize": "0x0",
    "Attributes": []
  },
  "DougTheDruid": {
    "Notes": "Generated by DougTheDruid#2784 on Discord",
    "Reference": "https://github.com/DougTheDruid"
  }
}