{
  "SplinePathingActor": {
    "Super": "Actor",
    "FullSize": "0x488",
    "InheritedSize": "0x3a0",
    "ClassSize": "0xe8",
    "Attributes": [
      {
        "Name": "pad0x8_W41SX[0x8]",
        "Type": "char",
        "Size": "0x8",
        "Offset": "0x3a0"
      },
      {
        "Name": "ObjectMessageDispatcher",
        "Type": "struct ObjectMessagingDispatcher",
        "Size": "0xa0",
        "Offset": "0x3a8"
      },
      {
        "Name": "pad0x10_W8REV[0x10]",
        "Type": "char",
        "Size": "0x10",
        "Offset": "0x448"
      },
      {
        "Name": "Root",
        "Type": "class SceneComponent*",
        "Size": "0x8",
        "Offset": "0x458"
      },
      {
        "Name": "Spline",
        "Type": "class SplineComponent*",
        "Size": "0x8",
        "Offset": "0x460"
      },
      {
        "Name": "Force",
        "Type": "float",
        "Size": "0x4",
        "Offset": "0x468"
      },
      {
        "Name": "MaxVelocity",
        "Type": "float",
        "Size": "0x4",
        "Offset": "0x46c"
      },
      {
        "Name": "DistanceAlongSplineToTarget",
        "Type": "float",
        "Size": "0x4",
        "Offset": "0x470"
      },
      {
        "Name": "DistanceFromDestination",
        "Type": "int",
        "Size": "0x4",
        "Offset": "0x474"
      },
      {
        "Name": "pad0x10_6B6O5[0x10]",
        "Type": "char",
        "Size": "0x10",
        "Offset": "0x478"
      }
    ]
  },
  "FixedSplinePathingActor": {
    "Super": "Actor",
    "FullSize": "0x3f0",
    "InheritedSize": "0x3a0",
    "ClassSize": "0x50",
    "Attributes": [
      {
        "Name": "Root",
        "Type": "class SceneComponent*",
        "Size": "0x8",
        "Offset": "0x3a0"
      },
      {
        "Name": "FakedBuoyancyComponent",
        "Type": "class FakedBuoyancyComponent*",
        "Size": "0x8",
        "Offset": "0x3a8"
      },
      {
        "Name": "Speed",
        "Type": "float",
        "Size": "0x4",
        "Offset": "0x3b0"
      },
      {
        "Name": "pad0x4_U5QBA[0x4]",
        "Type": "char",
        "Size": "0x4",
        "Offset": "0x3b4"
      },
      {
        "Name": "FollowingSpline",
        "Type": "class SplineComponent*",
        "Size": "0x8",
        "Offset": "0x3b8"
      },
      {
        "Name": "CanTick",
        "Type": "bool",
        "Size": "0x1",
        "Offset": "0x3c0"
      },
      {
        "Name": "pad0x2f_PZ8XI[0x2f]",
        "Type": "char",
        "Size": "0x2f",
        "Offset": "0x3c1"
      }
    ]
  },
  "DougTheDruid": {
    "Notes": "Generated by dougthedruid on Discord",
    "Reference": "https://github.com/DougTheDruid"
  }
}