{
  "FinaleReplicationState": {
    "ClassSize": "0x10",
    "Attributes": {
      "State": {
        "Type": "byte",
        "Size": "0x1",
        "Offset": "0x0"
      },
      "TargetEnsemble": {
        "Type": "Class Object*",
        "Size": "0x8",
        "Offset": "0x8"
      }
    }
  },
  "UnlockEventData": {
    "ClassSize": "0x4",
    "Attributes": {
      "Idx": {
        "Type": "int",
        "Size": "0x4",
        "Offset": "0x0"
      }
    }
  },
  "GlitterBeardVFXTransitionCompletedEvent": {
    "ClassSize": "0x4",
    "Attributes": {
      "Index": {
        "Type": "int",
        "Size": "0x4",
        "Offset": "0x0"
      }
    }
  },
  "ChangeGlitterBeardVFXStateEvent": {
    "ClassSize": "0x8",
    "Attributes": {
      "Index": {
        "Type": "int",
        "Size": "0x4",
        "Offset": "0x0"
      },
      "Target": {
        "Type": "byte",
        "Size": "0x1",
        "Offset": "0x4"
      }
    }
  },
  "GlitterbeardPuzzleCancelTelemetryEvent": {
    "ClassSize": "0x10",
    "Attributes": {}
  },
  "GlitterbeardPuzzleUnlockTelemetryEvent": {
    "ClassSize": "0x10",
    "Attributes": {}
  },
  "GlitterbeardPlayerPuzzleUnlockSuccessTelemetryEvent": {
    "ClassSize": "0x10",
    "Attributes": {}
  },
  "GlitterbeardPlayerPuzzleUnlockFailureTelemetryEvent": {
    "ClassSize": "0x20",
    "Attributes": {}
  },
  "GlitterbeardSessionEndTelemetryEvent": {
    "ClassSize": "0x10",
    "Attributes": {}
  },
  "GlitterbeardSessionBeginTelemetryEvent": {
    "ClassSize": "0x10",
    "Attributes": {}
  },
  "DougTheDruid": {
    "Notes": "Generated by DougTheDruid#2784 on Discord",
    "Reference": "https://github.com/DougTheDruid"
  }
}